nephyx_orm/__init__.py
nephyx_orm/model.py
nephyx_orm/py.typed
nephyx_orm/repository.py
nephyx_orm-0.0.2.dist-info/METADATA
nephyx_orm-0.0.2.dist-info/WHEEL
nephyx_orm-0.0.2.dist-info/top_level.txt
nephyx_orm-0.0.2.dist-info/RECORD
