Metadata-Version: 2.4
Name: nephyx-orm
Version: 0.0.2
Summary: Add your description here
Requires-Python: >=3.12
Requires-Dist: sqlalchemy>=2.0.40
